pyslider/__init__.py
pyslider/configs.py
pyslider/main.py
pyslider/static.py
pyslider/utils/__init__.py
pyslider-0.0.1.dist-info/METADATA
pyslider-0.0.1.dist-info/WHEEL
pyslider-0.0.1.dist-info/entry_points.txt
pyslider-0.0.1.dist-info/licenses/LICENSE
pyslider-0.0.1.dist-info/RECORD
