Metadata-Version: 2.4
Name: pyslider
Version: 0.0.1
Summary: Pyslider is a tool to create pdf slides from markdown
Project-URL: Homepage, https://github.com/veltzer/pyslider
Project-URL: Bug Tracker, https://github.com/veltzer/pyslider/issues
Project-URL: Documentation, https://veltzer.github.io/pyslider
Project-URL: Download, https://pypi.org/project/pyslider/
Project-URL: Repository, https://github.com/veltzer/pyslider
Author-email: Mark Veltzer <mark.veltzer@gmail.com>
Maintainer-email: Mark Veltzer <mark.veltzer@gmail.com>
License-Expression: MIT
License-File: LICENSE
Keywords: marp,pdf,powerpoint,slides
Classifier: Development Status :: 4 - Beta
Classifier: Environment :: Console
Classifier: License :: OSI Approved :: MIT License
Classifier: Operating System :: OS Independent
Classifier: Programming Language :: Python
Classifier: Programming Language :: Python :: 3
Classifier: Programming Language :: Python :: 3 :: Only
Classifier: Programming Language :: Python :: 3.12
Classifier: Topic :: Utilities
Requires-Python: >=3.12
